[{"id":16,"fetchid":511,"url":"https://replay.pokemonshowdown.com/smogtours-gen3ubers-911842?p2","team1":"latios.forretress.kyogre.snorlax.mewtwo.rayquaza.","team2":"latios.metagross.groudon.ho-oh.snorlax.deoxys-attack.","player1":"sadisticnarwhal","player2":"doso749","style1":"","style2":"","date":1771795080,"isASample":"","threadURL":"https://www.smogon.com/forums/threads/ancient-lower-tiers-premier-league-iv-replays.3776296/page-1","threadName":"ALTPL IV","threadRound":""},{"id":14,"fetchid":511,"url":"https://replay.pokemonshowdown.com/smogtours-gen3ubers-906959","team1":"deoxys-defense.blissey.dusclops.groudon.lugia.starmie.","team2":"mewtwo.blissey.jirachi.kyogre.latios..","player1":"a quylthulg","player2":"bp","style1":"","style2":"","date":1770568944,"isASample":"","threadURL":"https://www.smogon.com/forums/threads/ancient-lower-tiers-premier-league-iv-replays.3776296/page-1","threadName":"ALTPL IV","threadRound":""},{"id":13,"fetchid":511,"url":"https://replay.pokemonshowdown.com/smogtours-gen3ubers-905963?p2","team1":"latios.snorlax.exeggutor.ho-oh.groudon.rayquaza.","team2":"mewtwo.groudon.latios.wobbuffet.heracross.rayquaza.","player1":"kjdaas","player2":"plague","style1":"","style2":"","date":1770415041,"isASample":"","threadURL":"https://www.smogon.com/forums/threads/ancient-lower-tiers-premier-league-iv-replays.3776296/page-1","threadName":"ALTPL IV","threadRound":""},{"id":15,"fetchid":511,"url":"https://replay.pokemonshowdown.com/gen3ubers-2533652842-98ibtqe42mynjod7h75gnsutwgi0qjbpw","team1":"ho-oh.latios.snorlax.forretress.groudon.rayquaza.","team2":"groudon.lugia.blissey.ho-oh.forretress.latias.","player1":"DonBoneJones","player2":"doso749","style1":"","style2":"","date":1770326622,"isASample":"","threadURL":"https://www.smogon.com/forums/threads/ancient-lower-tiers-premier-league-iv-replays.3776296/page-1","threadName":"ALTPL IV","threadRound":""},{"id":10,"fetchid":511,"url":"https://replay.pokemonshowdown.com/smogtours-gen3ubers-904866","team1":"latios.snorlax.skarmory.groudon.deoxys-attack.metagross.","team2":"mewtwo.latios.metagross.groudon.deoxys-attack.mew.","player1":"plague","player2":"Zcarlett","style1":"","style2":"","date":1769980876,"isASample":"","threadURL":"https://www.smogon.com/forums/threads/ancient-lower-tiers-premier-league-iv-replays.3776296/page-1","threadName":"ALTPL IV","threadRound":""},{"id":11,"fetchid":511,"url":"https://replay.pokemonshowdown.com/smogtours-gen3ubers-904556?p2","team1":"kyogre.blissey.metagross.forretress.latios..","team2":"mewtwo.latios.groudon.metagross.snorlax.rayquaza.","player1":"Sadisticnarwhal","player2":"ST Alder","style1":"","style2":"","date":1769962680,"isASample":"","threadURL":"https://www.smogon.com/forums/threads/ancient-lower-tiers-premier-league-iv-replays.3776296/page-1","threadName":"ALTPL IV","threadRound":""},{"id":12,"fetchid":511,"url":"https://replay.pokemonshowdown.com/smogtours-gen3ubers-902969","team1":"metagross.blissey.forretress.kyogre.latios.rayquaza.","team2":"kyogre.snorlax.latios.forretress.kabutops.deoxys-attack.","player1":"doso749","player2":"3 blades","style1":"","style2":"","date":1769452131,"isASample":"","threadURL":"https://www.smogon.com/forums/threads/ancient-lower-tiers-premier-league-iv-replays.3776296/page-1","threadName":"ALTPL IV","threadRound":""},{"id":8,"fetchid":511,"url":"https://replay.pokemonshowdown.com/smogtours-gen3ubers-901980","team1":"mewtwo.kyogre.snorlax.latios.metagross.deoxys-attack.","team2":"groudon.ho-oh.latias.forretress.blissey.lugia.","player1":"doso749","player2":"a quylthulg","style1":"","style2":"","date":1769275237,"isASample":"","threadURL":"https://www.smogon.com/forums/threads/ancient-lower-tiers-premier-league-iv-replays.3776296/page-1","threadName":"ALTPL IV","threadRound":""},{"id":7,"fetchid":511,"url":"https://replay.pokemonshowdown.com/smogtours-gen3ubers-901487?p2","team1":"tyranitar.skarmory.lugia.blissey.mewtwo.latios.","team2":"mew.metagross.latios.snorlax.groudon.rayquaza.","player1":"sadisticnarwhal","player2":"3 blades","style1":"","style2":"","date":1769134867,"isASample":"","threadURL":"https://www.smogon.com/forums/threads/ancient-lower-tiers-premier-league-iv-replays.3776296/page-1","threadName":"ALTPL IV","threadRound":""},{"id":9,"fetchid":511,"url":"https://replay.pokemonshowdown.com/smogtours-gen3ubers-901470?p2","team1":"mewtwo.snorlax.kyogre.metagross.latios.deoxys-attack.","team2":"mew.groudon.latios.metagross.mewtwo.rayquaza.","player1":"EG Alder","player2":"plague","style1":"","style2":"","date":1769127927,"isASample":"","threadURL":"https://www.smogon.com/forums/threads/ancient-lower-tiers-premier-league-iv-replays.3776296/page-1","threadName":"ALTPL IV","threadRound":""},{"id":4,"fetchid":511,"url":"https://replay.pokemonshowdown.com/smogtours-gen3ubers-900550?p2","team1":"mewtwo.kyogre.latios.snorlax.omastar.deoxys-attack.","team2":"latias.kyogre.blissey.skarmory.gengar.salamence.","player1":"sadisticnarwhal","player2":"a quylthulg","style1":"","style2":"","date":1768767202,"isASample":"","threadURL":"https://www.smogon.com/forums/threads/ancient-lower-tiers-premier-league-iv-replays.3776296/page-1","threadName":"ALTPL IV","threadRound":""},{"id":5,"fetchid":511,"url":"https://replay.pokemonshowdown.com/smogtours-gen3ubers-900391","team1":"mewtwo.snorlax.latios.forretress.deoxys-attack.kyogre.","team2":"groudon.jirachi.gengar.blissey.skarmory.latios.","player1":"3 blades","player2":"EG Alder","style1":"","style2":"","date":1768753116,"isASample":"","threadURL":"https://www.smogon.com/forums/threads/ancient-lower-tiers-premier-league-iv-replays.3776296/page-1","threadName":"ALTPL IV","threadRound":""},{"id":6,"fetchid":511,"url":"https://replay.pokemonshowdown.com/gen3ubers-2520626346-29h6owagyadwe4mxh32minimsu4wt1hpw","team1":"groudon.blissey.skarmory.deoxys-attack.celebi.ho-oh.","team2":"kyogre.snorlax.latios.rayquaza.metagross.deoxys-attack.","player1":"doso749","player2":"plague","style1":"","style2":"","date":1768665189,"isASample":"","threadURL":"https://www.smogon.com/forums/threads/ancient-lower-tiers-premier-league-iv-replays.3776296/page-1","threadName":"ALTPL IV","threadRound":""},{"id":1,"fetchid":511,"url":"https://replay.pokemonshowdown.com/smogtours-gen3ubers-898719","team1":"groudon.snorlax.skarmory.latias.metagross.mewtwo.","team2":"mewtwo.forretress.blissey.kyogre.latios.rayquaza.","player1":"EG Alder","player2":"a quylthulg","style1":"","style2":"","date":1768102221,"isASample":"","threadURL":"https://www.smogon.com/forums/threads/ancient-lower-tiers-premier-league-iv-replays.3776296/page-1","threadName":"ALTPL IV","threadRound":""},{"id":3,"fetchid":511,"url":"https://replay.pokemonshowdown.com/smogtours-gen3ubers-897984","team1":"groudon.lugia.mewtwo.snorlax.aerodactyl..","team2":"groudon.skarmory.gengar.ho-oh.latias.blissey.","player1":"sadisticnarwhal","player2":"Rambode","style1":"","style2":"","date":1767917494,"isASample":"","threadURL":"https://www.smogon.com/forums/threads/ancient-lower-tiers-premier-league-iv-replays.3776296/page-1","threadName":"ALTPL IV","threadRound":""},{"id":2,"fetchid":511,"url":"https://replay.pokemonshowdown.com/smogtours-gen3ubers-897834?p2","team1":"mewtwo.kyogre.rayquaza.snorlax.omastar.latios.","team2":"heracross.deoxys-attack.latios.wobbuffet.groudon.rayquaza.","player1":"PLAGUE","player2":"3 blades","style1":"","style2":"","date":1767831241,"isASample":"","threadURL":"https://www.smogon.com/forums/threads/ancient-lower-tiers-premier-league-iv-replays.3776296/page-1","threadName":"ALTPL IV","threadRound":""},{"id":33,"fetchid":519,"url":"https://replay.pokemonshowdown.com/smogtours-gen3ubers-749500","team1":"mewtwo.metagross.latios.kyogre.snorlax.deoxys-attack.","team2":"latios.jirachi.groudon.deoxys-attack.snorlax.rayquaza.","player1":"sadisticnarwhal","player2":"temp","style1":"","style2":"","date":1708809752,"isASample":"","threadURL":"https://www.smogon.com/forums/threads/alt-pl-vol-2-replays-and-usage-statistics.3734367/page-1","threadName":"ALTPL II","threadRound":""},{"id":32,"fetchid":519,"url":"https://replay.pokemonshowdown.com/smogtours-gen3ubers-747526","team1":"groudon.blissey.forretress.deoxys-attack.ho-oh.latios.","team2":"kyogre.forretress.latios.blissey.rayquaza.deoxys-attack.","player1":"temp","player2":"Lasen","style1":"","style2":"","date":1708036029,"isASample":"","threadURL":"https://www.smogon.com/forums/threads/alt-pl-vol-2-replays-and-usage-statistics.3734367/page-1","threadName":"ALTPL II","threadRound":""},{"id":29,"fetchid":519,"url":"https://replay.pokemonshowdown.com/smogtours-gen3ubers-746841","team1":"groudon.snorlax.latios.magneton.rayquaza.deoxys-attack.","team2":"groudon.latias.snorlax.deoxys-attack.magneton.heracross.","player1":"ajencis","player2":"Alkione","style1":"","style2":"","date":1707685565,"isASample":"","threadURL":"https://www.smogon.com/forums/threads/alt-pl-vol-2-replays-and-usage-statistics.3734367/page-1","threadName":"ALTPL II","threadRound":""},{"id":31,"fetchid":519,"url":"https://replay.pokemonshowdown.com/smogtours-gen3ubers-746195","team1":"heracross.latios.deoxys-attack.snorlax.gyarados.metagross.","team2":"deoxys-defense.salamence.blissey.groudon.latias.ho-oh.","player1":"temp","player2":"Rhmsitb","style1":"","style2":"","date":1707581879,"isASample":"","threadURL":"https://www.smogon.com/forums/threads/alt-pl-vol-2-replays-and-usage-statistics.3734367/page-1","threadName":"ALTPL II","threadRound":""},{"id":30,"fetchid":519,"url":"https://replay.pokemonshowdown.com/smogtours-gen3ubers-745944?p2","team1":"deoxys-defense.lugia.blissey.metagross.mewtwo.latias.","team2":"latios.metagross.snorlax.ho-oh.groudon.mewtwo.","player1":"Piyush21","player2":"Frrf","style1":"","style2":"","date":1707499214,"isASample":"","threadURL":"https://www.smogon.com/forums/threads/alt-pl-vol-2-replays-and-usage-statistics.3734367/page-1","threadName":"ALTPL II","threadRound":""},{"id":28,"fetchid":519,"url":"https://replay.pokemonshowdown.com/smogtours-gen3ubers-744811?p2","team1":"mewtwo.metagross.snorlax.latios.deoxys-attack..","team2":"latios.kyogre.wobbuffet.metagross.mewtwo.deoxys-attack.","player1":"seroo","player2":"Rhmsitb","style1":"","style2":"","date":1707064326,"isASample":"","threadURL":"https://www.smogon.com/forums/threads/alt-pl-vol-2-replays-and-usage-statistics.3734367/page-1","threadName":"ALTPL II","threadRound":""},{"id":26,"fetchid":519,"url":"https://replay.pokemonshowdown.com/smogtours-gen3ubers-744441","team1":"kyogre.blissey.latios.metagross.wobbuffet.deoxys-attack.","team2":"deoxys-speed.latios.jirachi.groudon.ho-oh.lugia.","player1":"Frrf","player2":"Alkione","style1":"","style2":"","date":1706991843,"isASample":"","threadURL":"https://www.smogon.com/forums/threads/alt-pl-vol-2-replays-and-usage-statistics.3734367/page-1","threadName":"ALTPL II","threadRound":""},{"id":27,"fetchid":519,"url":"https://replay.pokemonshowdown.com/smogtours-gen3ubers-743949","team1":"kyogre.blissey.skarmory.latios.gengar.deoxys-attack.","team2":"ho-oh.latias.metagross.groudon.snorlax.deoxys-attack.","player1":"sadisticnarwhal","player2":"temp","style1":"","style2":"","date":1706833722,"isASample":"","threadURL":"https://www.smogon.com/forums/threads/alt-pl-vol-2-replays-and-usage-statistics.3734367/page-1","threadName":"ALTPL II","threadRound":""},{"id":23,"fetchid":519,"url":"https://replay.pokemonshowdown.com/smogtours-gen3ubers-743187","team1":"tauros.latios.kyogre.deoxys-attack.metagross.kabutops.","team2":"kyogre.blissey.forretress.latias.deoxys-attack.snorlax.","player1":"temp","player2":"Alkione","style1":"","style2":"","date":1706483600,"isASample":"","threadURL":"https://www.smogon.com/forums/threads/alt-pl-vol-2-replays-and-usage-statistics.3734367/page-1","threadName":"ALTPL II","threadRound":""},{"id":25,"fetchid":519,"url":"https://replay.pokemonshowdown.com/smogtours-gen3ubers-742967","team1":"groudon.snorlax.ho-oh.latios.metagross.deoxys-attack.","team2":"kyogre.forretress.snorlax.latios.deoxys-attack.mewtwo.","player1":"sadisticnarwhal","player2":"Beleth7rei","style1":"","style2":"","date":1706469678,"isASample":"","threadURL":"https://www.smogon.com/forums/threads/alt-pl-vol-2-replays-and-usage-statistics.3734367/page-1","threadName":"ALTPL II","threadRound":""},{"id":24,"fetchid":519,"url":"https://replay.pokemonshowdown.com/smogtours-gen3ubers-742170?p2","team1":"kyogre.blissey.forretress.gengar.rayquaza.latios.","team2":"mew.latias.metagross.kyogre.snorlax.mewtwo.","player1":"Frrf","player2":"Rhmsitb","style1":"","style2":"","date":1706364526,"isASample":"","threadURL":"https://www.smogon.com/forums/threads/alt-pl-vol-2-replays-and-usage-statistics.3734367/page-1","threadName":"ALTPL II","threadRound":""},{"id":22,"fetchid":519,"url":"https://replay.pokemonshowdown.com/smogtours-gen3ubers-741006?p2","team1":"heracross.groudon.ho-oh.metagross.latios.deoxys-attack.","team2":"mewtwo.latios.groudon.metagross.mew.deoxys-attack.","player1":"ajencis","player2":"Frrf","style1":"","style2":"","date":1705863758,"isASample":"","threadURL":"https://www.smogon.com/forums/threads/alt-pl-vol-2-replays-and-usage-statistics.3734367/page-1","threadName":"ALTPL II","threadRound":""},{"id":20,"fetchid":519,"url":"https://replay.pokemonshowdown.com/smogtours-gen3ubers-740700?p2","team1":"latios.wobbuffet.metagross.kyogre.deoxys-attack..","team2":"kyogre.metagross.snorlax.deoxys-attack.latias.magneton.","player1":"Rhmsitb","player2":"Alkione","style1":"","style2":"","date":1705849994,"isASample":"","threadURL":"https://www.smogon.com/forums/threads/alt-pl-vol-2-replays-and-usage-statistics.3734367/page-1","threadName":"ALTPL II","threadRound":""},{"id":21,"fetchid":519,"url":"https://replay.pokemonshowdown.com/smogtours-gen3ubers-739861","team1":"ho-oh.blissey.deoxys-defense.salamence.latias.groudon.","team2":"groudon.blissey.skarmory.umbreon.latias.ho-oh.","player1":"temp","player2":"Beleth7rei","style1":"","style2":"","date":1705605835,"isASample":"","threadURL":"https://www.smogon.com/forums/threads/alt-pl-vol-2-replays-and-usage-statistics.3734367/page-1","threadName":"ALTPL II","threadRound":""},{"id":19,"fetchid":519,"url":"https://replay.pokemonshowdown.com/smogtours-gen3ubers-739314","team1":"deoxys-attack.dugtrio.snorlax.kyogre.latias.forretress.","team2":"mewtwo.metagross.latios.groudon.snorlax.rayquaza.","player1":"temp","player2":"Frrf","style1":"","style2":"","date":1705262536,"isASample":"","threadURL":"https://www.smogon.com/forums/threads/alt-pl-vol-2-replays-and-usage-statistics.3734367/page-1","threadName":"ALTPL II","threadRound":""},{"id":18,"fetchid":519,"url":"https://replay.pokemonshowdown.com/smogtours-gen3ubers-738946","team1":"ho-oh.metagross.latias.groudon.snorlax.deoxys-attack.","team2":"deoxys-defense.lugia.forretress.blissey.groudon.latias.","player1":"Rhmsitb","player2":"ajencis","style1":"","style2":"","date":1705124181,"isASample":"","threadURL":"https://www.smogon.com/forums/threads/alt-pl-vol-2-replays-and-usage-statistics.3734367/page-1","threadName":"ALTPL II","threadRound":""},{"id":17,"fetchid":519,"url":"https://replay.pokemonshowdown.com/smogtours-gen3ubers-738872?p2","team1":"groudon.blissey.skarmory.latios.snorlax.deoxys-attack.","team2":"mewtwo.latios.metagross.deoxys-attack.groudon.smeargle.","player1":"Alkione","player2":"Beleth7rei","style1":"","style2":"","date":1705091511,"isASample":"","threadURL":"https://www.smogon.com/forums/threads/alt-pl-vol-2-replays-and-usage-statistics.3734367/page-1","threadName":"ALTPL II","threadRound":""}]