[{"id":1,"fetchid":140,"url":"https://replay.pokemonshowdown.com/smogtours-gen5ubers-450800?p2","team1":"politoed.keldeo.thundurus-therian.celebi.excadrill.tyranitar.","team2":"politoed.ferrothorn.skarmory.chansey.tentacruel.gothitelle.","player1":"Conflict","player2":"WBest","style1":"","style2":"","date":1562448156,"isASample":"","threadURL":"https://www.smogon.com/forums/threads/the-world-cup-of-pok%C3%A9mon-2019-replays.3650498/page-1","threadName":"WCUP 2019","threadRound":""},{"id":2,"fetchid":810,"url":"https://replay.pokemonshowdown.com/pokemononline-gen5ubers-4","team1":"groudon.dialga.deoxys-attack.arceus.palkia.victini.","team2":"deoxys-speed.rayquaza.palkia.mewtwo.groudon.arceus.","player1":"ciele","player2":"nelsonx","style1":"","style2":"","date":1353324720,"isASample":"","threadURL":"https://www.smogon.com/forums/threads/chubbins-archive-of-restored-replays.3756803/page-1","threadName":"Restored Replays","threadRound":""}]